{"type": "Feature", "id": 12512530, "properties": {"woe:id": 12512530, "woe:parent_id": 24929799, "woe:name": "Jicin Airport", "woe:placetype": 14, "woe:placetype_name": "Airport", "woe:lang": "ENG", "iso:country": "CZ", "meta:provider": ["geoplanet:7.3.1", "geoplanet:7.3.2", "geoplanet:7.4.0", "geoplanet:7.4.1", "geoplanet:7.5.1", "geoplanet:7.5.2", "geoplanet:7.6.0", "geoplanet:7.8.1", "geoplanet:7.9.0", "geoplanet:7.10.0", "geoplanet:8.0.0", "woeplanet:8.0.0"], "meta:indexed": "2020-08-20T20:27:45.329204", "woe:alias_UNK_V": ["Letiste Jicin"], "meta:updated": "2020-08-22T02:41:02.546627", "woe:hierarchy": {"continent": 24865675, "country": 23424810, "town": 0, "planet": 1, "county": 12582596, "suburb": 0, "state": 20070466, "region": 0, "localadmin": 12609370}, "woe:timezone_id": 28350912, "woe:hash": "u2fyusr3ruz5", "woe:centroid": [15.32524, 50.42886], "geom:latitude": 50.42886, "geom:longitude": 15.32524, "geom:hash": "u2fyusr3ruz5", "woe:latitude": 50.42886, "geom:centroid": [15.32524, 50.42886], "woe:longitude": 15.32524, "woe:repo": "woeplanet-airport-cz"}, "geometry": {"coordinates": [15.32524, 50.42886], "type": "Point"}}