{"type": "Feature", "id": 56049686, "geometry": {"type": "Point", "coordinates": [16.06756, 48.818619]}, "properties": {"woe:id": 56049686, "woe:parent_id": 802222, "woe:name": "Letiste Znojmo", "woe:placetype": 14, "woe:placetype_name": "Airport", "woe:lang": "CZE", "iso:country": "CZ", "meta:provider": ["geoplanet:7.3.1", "geoplanet:7.3.2", "geoplanet:7.4.0", "geoplanet:7.4.1", "geoplanet:7.5.1", "geoplanet:7.5.2", "geoplanet:7.6.0", "geoplanet:7.8.1", "geoplanet:7.9.0", "geoplanet:7.10.0", "geoplanet:8.0.0", "woeplanet:8.0.0"], "meta:indexed": "2020-08-20T20:27:45.274449", "meta:updated": "2020-10-14T11:22:11.638015", "woe:hierarchy": {"continent": 24865675, "country": 23424810, "town": 0, "planet": 1, "county": 12582558, "suburb": 0, "state": 20070503, "region": 0, "localadmin": 12605512}, "woe:timezone_id": 28350912, "woe:hash": "u2emtxhj161j", "woe:centroid": [16.06756, 48.818619], "geom:latitude": 48.818619, "geom:longitude": 16.06756, "geom:hash": "u2emtxhj161j", "woe:latitude": 48.818619, "geom:centroid": [16.06756, 48.818619], "woe:longitude": 16.06756, "woe:repo": "woeplanet-airport-cz", "geom:area": 0.0, "woe:scale": 19}}