{"type": "Feature", "id": 56049693, "properties": {"woe:id": 56049693, "woe:parent_id": 789992, "woe:name": "Aeroklub Horovice", "woe:placetype": 14, "woe:placetype_name": "Airport", "woe:lang": "CZE", "iso:country": "CZ", "meta:provider": ["geoplanet:7.3.1", "geoplanet:7.3.2", "geoplanet:7.4.0", "geoplanet:7.4.1", "geoplanet:7.5.1", "geoplanet:7.5.2", "geoplanet:7.6.0", "geoplanet:7.8.1", "geoplanet:7.9.0", "geoplanet:7.10.0", "geoplanet:8.0.0", "woeplanet:8.0.0"], "meta:indexed": "2020-08-20T20:27:45.280359", "meta:updated": "2020-08-22T02:41:02.528657", "woe:hierarchy": {"continent": 24865675, "country": 23424810, "town": 0, "planet": 1, "county": 12582582, "suburb": 0, "state": 20070468, "region": 0, "localadmin": 12608790}, "woe:timezone_id": 28350912, "woe:hash": "u2cgs40xux30", "woe:centroid": [13.8876, 49.84634], "geom:latitude": 49.84634, "geom:longitude": 13.8876, "geom:hash": "u2cgs40xux30", "woe:latitude": 49.84634, "geom:centroid": [13.8876, 49.84634], "woe:longitude": 13.8876, "woe:repo": "woeplanet-airport-cz"}, "geometry": {"coordinates": [13.8876, 49.84634], "type": "Point"}}