{"type": "Feature", "id": 56049719, "geometry": {"type": "Point", "coordinates": [13.97059, 50.698898]}, "properties": {"woe:id": 56049719, "woe:parent_id": 800260, "woe:name": "Letiste Usti Nad Labem", "woe:placetype": 14, "woe:placetype_name": "Airport", "woe:lang": "CZE", "iso:country": "CZ", "meta:provider": ["geoplanet:7.3.1", "geoplanet:7.3.2", "geoplanet:7.4.0", "geoplanet:7.4.1", "geoplanet:7.5.1", "geoplanet:7.5.2", "geoplanet:7.6.0", "geoplanet:7.8.1", "geoplanet:7.9.0", "geoplanet:7.10.0", "geoplanet:8.0.0", "woeplanet:8.0.0"], "meta:indexed": "2020-08-20T20:27:45.354574", "meta:updated": "2020-10-14T11:22:11.661875", "woe:hierarchy": {"continent": 24865675, "country": 23424810, "town": 0, "planet": 1, "county": 12582569, "suburb": 0, "state": 20070499, "region": 0, "localadmin": 12606615}, "woe:timezone_id": 28350912, "woe:hash": "u31bmvmn6rdf", "woe:centroid": [13.97059, 50.698898], "geom:latitude": 50.698898, "geom:longitude": 13.97059, "geom:hash": "u31bmvmn6rdf", "woe:latitude": 50.698898, "geom:centroid": [13.97059, 50.698898], "woe:longitude": 13.97059, "woe:repo": "woeplanet-airport-cz", "geom:area": 0.0, "woe:scale": 19}}