{"type": "Feature", "id": 12512538, "properties": {"woe:id": 12512538, "woe:parent_id": 786945, "woe:name": "Kozolupy Bubovice Airport", "woe:placetype": 14, "woe:placetype_name": "Airport", "woe:lang": "ENG", "iso:country": "CZ", "meta:provider": ["geoplanet:7.3.1", "geoplanet:7.3.2", "geoplanet:7.4.0", "geoplanet:7.4.1", "geoplanet:7.5.1", "geoplanet:7.5.2", "geoplanet:7.6.0", "geoplanet:7.8.1", "geoplanet:7.9.0", "geoplanet:7.10.0", "geoplanet:8.0.0", "woeplanet:8.0.0"], "meta:indexed": "2020-08-20T20:27:45.225069", "meta:updated": "2020-08-22T02:41:02.507894", "woe:hierarchy": {"continent": 24865675, "country": 23424810, "town": 0, "planet": 1, "county": 12582582, "suburb": 0, "state": 20070468, "region": 0, "localadmin": 12607906}, "woe:timezone_id": 28350912, "woe:hash": "u2fh69nnfm0m", "woe:centroid": [14.1807, 49.9725], "geom:latitude": 49.9725, "geom:longitude": 14.1807, "geom:hash": "u2fh69nnfm0m", "woe:latitude": 49.9725, "geom:centroid": [14.1807, 49.9725], "woe:longitude": 14.1807, "woe:repo": "woeplanet-airport-cz"}, "geometry": {"coordinates": [14.1807, 49.9725], "type": "Point"}}