{"type": "Feature", "id": 56049673, "properties": {"woe:id": 56049673, "woe:parent_id": 788060, "woe:name": "Letiste Bynovec", "woe:placetype": 14, "woe:placetype_name": "Airport", "woe:lang": "CZE", "iso:country": "CZ", "meta:provider": ["geoplanet:7.3.1", "geoplanet:7.3.2", "geoplanet:7.4.0", "geoplanet:7.4.1", "geoplanet:7.5.1", "geoplanet:7.5.2", "geoplanet:7.6.0", "geoplanet:7.8.1", "geoplanet:7.9.0", "geoplanet:7.10.0", "geoplanet:8.0.0", "woeplanet:8.0.0"], "meta:indexed": "2020-08-20T20:27:45.265741", "meta:updated": "2020-08-22T02:41:02.524091", "woe:hierarchy": {"continent": 24865675, "country": 23424810, "town": 0, "planet": 1, "county": 12582562, "suburb": 0, "state": 20070499, "region": 0, "localadmin": 12606653}, "woe:timezone_id": 28350912, "woe:hash": "u341hsw7rq32", "woe:centroid": [14.26915, 50.826092], "geom:latitude": 50.826092, "geom:longitude": 14.26915, "geom:hash": "u341hsw7rq32", "woe:latitude": 50.826092, "geom:centroid": [14.26915, 50.826092], "woe:longitude": 14.26915, "woe:repo": "woeplanet-airport-cz"}, "geometry": {"coordinates": [14.26915, 50.826092], "type": "Point"}}