{"type": "Feature", "id": 12512526, "geometry": {"type": "Point", "coordinates": [15.5758, 50.355]}, "properties": {"woe:id": 12512526, "woe:parent_id": 788693, "woe:name": "Horice Airport", "woe:placetype": 14, "woe:placetype_name": "Airport", "woe:lang": "ENG", "iso:country": "CZ", "meta:provider": ["geoplanet:7.3.1", "geoplanet:7.3.2", "geoplanet:7.4.0", "geoplanet:7.4.1", "geoplanet:7.5.1", "geoplanet:7.5.2", "geoplanet:7.6.0", "geoplanet:7.8.1", "geoplanet:7.9.0", "geoplanet:7.10.0", "geoplanet:8.0.0", "woeplanet:8.0.0"], "meta:indexed": "2020-08-20T20:27:45.215352", "meta:updated": "2020-10-14T11:22:11.742522", "woe:hierarchy": {"continent": 24865675, "country": 23424810, "town": 0, "planet": 1, "county": 12582596, "suburb": 0, "state": 20070466, "region": 0, "localadmin": 12609299}, "woe:timezone_id": 28350912, "woe:hash": "u2gn6qvgnkq7", "woe:centroid": [15.5758, 50.355], "geom:latitude": 50.355, "geom:longitude": 15.5758, "geom:hash": "u2gn6qvgnkq7", "woe:latitude": 50.355, "geom:centroid": [15.5758, 50.355], "woe:longitude": 15.5758, "woe:repo": "woeplanet-airport-cz", "geom:area": 0.0, "woe:scale": 19}}