{"type": "Feature", "id": 12512569, "geometry": {"type": "Point", "coordinates": [14.0598, 49.0765]}, "properties": {"woe:id": 12512569, "woe:parent_id": 802102, "woe:name": "Strunkovice Airport", "woe:placetype": 14, "woe:placetype_name": "Airport", "woe:lang": "ENG", "iso:country": "CZ", "meta:provider": ["geoplanet:7.3.1", "geoplanet:7.3.2", "geoplanet:7.4.0", "geoplanet:7.4.1", "geoplanet:7.5.1", "geoplanet:7.5.2", "geoplanet:7.6.0", "geoplanet:7.8.1", "geoplanet:7.9.0", "geoplanet:7.10.0", "geoplanet:8.0.0", "woeplanet:8.0.0"], "meta:indexed": "2020-08-20T20:27:45.248237", "meta:updated": "2020-10-14T11:22:11.714955", "woe:hierarchy": {"continent": 24865675, "country": 23424810, "town": 0, "planet": 1, "county": 12582542, "suburb": 0, "state": 20070502, "region": 0, "localadmin": 12604698}, "woe:timezone_id": 28350912, "woe:hash": "u29zpyn534dt", "woe:centroid": [14.0598, 49.0765], "geom:latitude": 49.0765, "geom:longitude": 14.0598, "geom:hash": "u29zpyn534dt", "woe:latitude": 49.0765, "geom:centroid": [14.0598, 49.0765], "woe:longitude": 14.0598, "woe:repo": "woeplanet-airport-cz", "geom:area": 0.0, "woe:scale": 19}}