{"type": "Feature", "id": 12512567, "geometry": {"type": "Point", "coordinates": [13.0549, 49.560699]}, "properties": {"woe:id": 12512567, "woe:parent_id": 798602, "woe:name": "Stankov Airport", "woe:placetype": 14, "woe:placetype_name": "Airport", "woe:lang": "ENG", "iso:country": "CZ", "meta:provider": ["geoplanet:7.3.1", "geoplanet:7.3.2", "geoplanet:7.4.0", "geoplanet:7.4.1", "geoplanet:7.5.1", "geoplanet:7.5.2", "geoplanet:7.6.0", "geoplanet:7.8.1", "geoplanet:7.9.0", "geoplanet:7.10.0", "geoplanet:8.0.0", "woeplanet:8.0.0"], "meta:indexed": "2020-08-20T20:27:45.246326", "meta:updated": "2020-10-14T11:22:11.729166", "woe:hierarchy": {"continent": 24865675, "country": 23424810, "town": 0, "planet": 1, "county": 12582605, "suburb": 0, "state": 20070501, "region": 0, "localadmin": 12610003}, "woe:timezone_id": 28350912, "woe:hash": "u2c3cn4rcpyv", "woe:centroid": [13.0549, 49.560699], "geom:latitude": 49.560699, "geom:longitude": 13.0549, "geom:hash": "u2c3cn4rcpyv", "woe:latitude": 49.560699, "geom:centroid": [13.0549, 49.560699], "woe:longitude": 13.0549, "woe:repo": "woeplanet-airport-cz", "geom:area": 0.0, "woe:scale": 19}}